sila2_feature_lib/__init__.py
sila2_feature_lib/load.py
sila2_feature_lib/datastore/v001_0/datastore.sila.xml
sila2_feature_lib/datastore/v001_0/feature_ul.py
sila2_feature_lib/datastore/v001_0/extras/resource_handle.py
sila2_feature_lib/labwaremanipulator/v001_0/feature_ul.py
sila2_feature_lib/labwaremanipulator/v001_0/labwaremanipulator.sila.xml
sila2_feature_lib/labwaremanipulator/v001_0/types/sila_types.py
sila2_feature_lib/labwaresite/v001_0/feature_ul.py
sila2_feature_lib/labwaresite/v001_0/labwaresite.sila.xml
sila2_feature_lib/labwaresite/v001_0/types/sila_types.py
sila2_feature_lib/reportgen/v001_0/feature_ul.py
sila2_feature_lib/resource/v001_0/feature_ul.py
sila2_feature_lib/resource/v001_0/util/communication.py
sila2_feature_lib/resource/v001_0/util/grpc.py
sila2_feature_lib/simulation/v001_0/feature_ul.py
sila2_feature_lib/simulation/v001_0/simulation.sila.xml
sila2_feature_lib/workflowrunner/v001_0/feature_ul.py
sila2_feature_lib-2025.30a1.dist-info/licenses/AUTHORS.rst
sila2_feature_lib-2025.30a1.dist-info/licenses/LICENSE
sila2_feature_lib-2025.30a1.dist-info/METADATA
sila2_feature_lib-2025.30a1.dist-info/WHEEL
sila2_feature_lib-2025.30a1.dist-info/top_level.txt
sila2_feature_lib-2025.30a1.dist-info/RECORD
