Metadata-Version: 2.4
Name: sila2-feature-lib
Version: 2025.30a1
Summary: SiLA2 feature library
Author-email: Erik Trygg <etrg@novonordisk.com>
License: MIT
Project-URL: Homepage, https://github.com/Firefly78/sila2-feature-lib
Project-URL: Repository, https://github.com/Firefly78/sila2-feature-lib
Project-URL: Bug Tracker, https://github.com/Firefly78/sila2-feature-lib/issues
Classifier: Development Status :: 3 - Alpha
Classifier: License :: OSI Approved :: MIT License
Classifier: Operating System :: OS Independent
Classifier: Programming Language :: Python :: 3
Requires-Python: >=3.9
License-File: LICENSE
License-File: AUTHORS.rst
Provides-Extra: sila2
Requires-Dist: sila2; extra == "sila2"
Provides-Extra: unitelabs
Requires-Dist: unitelabs-cdk>=0.2.7; extra == "unitelabs"
Provides-Extra: httpx
Requires-Dist: httpx; extra == "httpx"
Provides-Extra: dev
Requires-Dist: black==24.4.2; extra == "dev"
Requires-Dist: bumpver; extra == "dev"
Requires-Dist: flake8==7.0.0; extra == "dev"
Requires-Dist: isort==5.13.2; extra == "dev"
Provides-Extra: test
Requires-Dist: pytest; extra == "test"
Dynamic: license-file
